README.md
setup.py
bin/hausschrat
hausschrat/__init__.py
hausschrat.egg-info/PKG-INFO
hausschrat.egg-info/SOURCES.txt
hausschrat.egg-info/dependency_links.txt
hausschrat.egg-info/top_level.txt
hausschrat.egg-info/zip-safe