Metadata-Version: 2.1
Name: hausschrat
Version: 1
Summary: hausschrat ssh ca cli
Home-page: https://git.osuv.de/m/hausschrat
Author: Markus Bergholz
Author-email: git@osuv.de  
License: WTFPL
Platform: UNKNOWN
